dicomaster.py
dicomaster-0.9.3.post1.dist-info/LICENSE.txt
dicomaster-0.9.3.post1.dist-info/METADATA
dicomaster-0.9.3.post1.dist-info/WHEEL
dicomaster-0.9.3.post1.dist-info/entry_points.txt
dicomaster-0.9.3.post1.dist-info/top_level.txt
dicomaster-0.9.3.post1.dist-info/RECORD
