Metadata-Version: 2.1
Name: dicomaster
Version: 0.9.3.post1
Summary: Secure DICOM Anonymizer & Batch Processor
Author-email: Santo Paul <santopaul2005@gmail.com>
Maintainer-email: Santo Paul <santopaul2005@gmail.com>
License: MIT
Project-URL: Homepage, https://github.com/santopaul/dicomaster
Project-URL: Repository, https://github.com/santopaul/dicomaster.git
Project-URL: Documentation, https://github.com/santopaul/dicomaster/blob/main/README.md
Project-URL: Bug Tracker, https://github.com/santopaul/dicomaster/issues
Keywords: dicom,anonymize,medical-imaging,pydicom,healthcare,radiology
Classifier: Development Status :: 4 - Beta
Classifier: Intended Audience :: Healthcare Industry
Classifier: Intended Audience :: Science/Research
Classifier: Operating System :: OS Independent
Classifier: Programming Language :: Python :: 3
Classifier: Programming Language :: Python :: 3.9
Classifier: Programming Language :: Python :: 3.10
Classifier: Programming Language :: Python :: 3.11
Classifier: Programming Language :: Python :: 3.12
Classifier: Topic :: Scientific/Engineering :: Medical Science Apps.
Classifier: Topic :: Security :: Cryptography
Requires-Python: >=3.9
License-File: LICENSE.txt
Requires-Dist: pydicom>=3.0.1
Requires-Dist: colorama>=0.4.6
Provides-Extra: dev
Requires-Dist: black>=24.3.0; extra == "dev"
Requires-Dist: ruff>=0.6.0; extra == "dev"
Requires-Dist: isort>=5.13.0; extra == "dev"
Requires-Dist: pytest>=7.4.0; extra == "dev"
Requires-Dist: pytest-cov>=4.1.0; extra == "dev"
Requires-Dist: mypy>=1.5.0; extra == "dev"
Requires-Dist: pre-commit>=3.7.0; extra == "dev"
Provides-Extra: full
Requires-Dist: cryptography>=46.0.3; extra == "full"
Requires-Dist: pandas>=2.0.0; extra == "full"
Requires-Dist: Pillow>=12.0.0; extra == "full"
Requires-Dist: tqdm>=4.65.0; extra == "full"
Requires-Dist: python-dateutil>=2.8.2; extra == "full"
Requires-Dist: numpy>=1.24; extra == "full"
Requires-Dist: pyfiglet>=0.8.post1; extra == "full"
Requires-Dist: termcolor>=2.3.0; extra == "full"
Requires-Dist: pytest>=7.4.0; extra == "full"
Requires-Dist: pytest-cov>=4.1.0; extra == "full"
Requires-Dist: mypy>=1.5.0; extra == "full"
Requires-Dist: ruff>=0.1.0; extra == "full"
Requires-Dist: build>=1.0.0; extra == "full"
Requires-Dist: twine>=6.2.0; extra == "full"
Provides-Extra: test
Requires-Dist: pytest>=7.4.0; extra == "test"
Requires-Dist: pytest-cov>=4.1.0; extra == "test"
Requires-Dist: mypy>=1.5.0; extra == "test"
Requires-Dist: ruff>=0.0.290; extra == "test"
